{
   "abstract" : "Deterministic schema contracts for flat files",
   "author" : [
      "Sergio de Sousa <sergio@serso.com>"
   ],
   "dynamic_config" : 0,
   "generated_by" : "Minilla/v3.1.29",
   "license" : [
      "perl_5"
   ],
   "meta-spec" : {
      "url" : "http://search.cpan.org/perldoc?CPAN::Meta::Spec",
      "version" : "2"
   },
   "name" : "Flat-Schema",
   "no_index" : {
      "directory" : [
         "t",
         "xt",
         "inc",
         "share",
         "eg",
         "examples",
         "author",
         "builder"
      ]
   },
   "prereqs" : {
      "configure" : {
         "requires" : {
            "Module::Build::Tiny" : "0.035"
         }
      },
      "develop" : {
         "requires" : {
            "Test::CPAN::Meta" : "0",
            "Test::MinimumVersion::Fast" : "0.04",
            "Test::PAUSE::Permissions" : "0.07",
            "Test::Pod" : "1.41",
            "Test::Spellunker" : "v0.2.7"
         }
      },
      "runtime" : {
         "requires" : {
            "Carp" : "0",
            "Encode" : "0",
            "ExtUtils::MakeMaker" : "0",
            "Module::Metadata" : "0",
            "Moo" : "0",
            "Pod::Escapes" : "0",
            "perl" : "5.032000"
         }
      },
      "test" : {
         "requires" : {
            "Test::More" : "0"
         }
      }
   },
   "provides" : {
      "Flat::Schema" : {
         "file" : "lib/Flat/Schema.pm",
         "version" : "0.01"
      }
   },
   "release_status" : "stable",
   "resources" : {
      "bugtracker" : {
         "web" : "https://github.com/sergio-desousa/Flat-Schema/issues"
      },
      "homepage" : "https://github.com/sergio-desousa/Flat-Schema",
      "repository" : {
         "type" : "git",
         "url" : "https://github.com/sergio-desousa/Flat-Schema.git",
         "web" : "https://github.com/sergio-desousa/Flat-Schema"
      }
   },
   "version" : "0.01",
   "x_authority" : "cpan:SDS",
   "x_serialization_backend" : "JSON::PP version 4.16",
   "x_static_install" : 1
}
